<?xml version="1.0" encoding="utf-8"?>
<limbo>
  <filters>
    <!-- create filters for repositories -->
    <repository id="mcpbot-issues">
      <ref id="mcpbot-issues"/>
    </repository>
    <repository id="ore">
      <ref id="ore"/>
    </repository>
    <repository id="paper">
      <ref id="paper"/>
    </repository>
    <repository id="spongeapi">
      <ref id="spongeapi"/>
    </repository>
    <repository id="spongecommon">
      <ref id="spongecommon"/>
    </repository>
    <repository id="spongeforge">
      <ref id="spongeforge"/>
    </repository>
    <repository id="spongevanilla">
      <ref id="spongevanilla"/>
    </repository>

    <!-- pull request comment/open by author/collaborator-->
    <all id="pr-co-ac">
      <any>
        <actor>author</actor>
        <actor>collaborator</actor>
      </any>
      <any>
        <event>pull request comment</event>
        <event>pull request open</event>
      </any>
    </all>

    <!-- pull request comment by collaborator-->
    <all id="pr-c-c">
      <actor>collaborator</actor>
      <event>pull request comment</event>
    </all>

    <event id="is-o">issue open</event>
    <event id="pr-o">pull request open</event>

    <!-- self (bot) actor -->
    <actor id="is-self">self</actor>
    <not id="not-self">
      <ref id="is-self"/>
    </not>

    <!-- issue open by anyone but self -->
    <all id="is-o-ns">
      <ref id="is-o"/>
      <ref id="not-self"/>
    </all>
    <!-- pull request open by anyone but self -->
    <all id="pr-o-ns">
      <ref id="pr-o"/>
      <ref id="not-self"/>
    </all>
  </filters>
</limbo>